LICENSE
MANIFEST.in
README.md
setup.py
flask_dataview/__init__.py
flask_dataview/extension.py
flask_dataview/helper.py
flask_dataview/models.py
flask_dataview.egg-info/PKG-INFO
flask_dataview.egg-info/SOURCES.txt
flask_dataview.egg-info/dependency_links.txt
flask_dataview.egg-info/requires.txt
flask_dataview.egg-info/top_level.txt
flask_dataview/static/echarts/js/echarts.min.js
flask_dataview/static/echarts/js/echarts.widget.js
flask_dataview/static/echarts/js/jquery.ui.widget.js
flask_dataview/static/echarts/js/jscolor.js
flask_dataview/static/echarts/js/some.theme.js
flask_dataview/templates/chart.html