Metadata-Version: 2.1
Name: flask-dataview
Version: 0.3.3
Summary: Flask Data Visualization Helpers
Home-page: https://github.com/wuttem/flask-dataview
Download-URL: https://github.com/wuttem
Author: Matthias Wutte
Author-email: matthias.wutte@gmail.com
License-File: LICENSE
